{
  "configuration": {
    "contentType": "organization",
    "fields": [
      { "name": "source",            "semanticType": "source_identifier", "participatesInMatching": false },
      { "name": "organization_name", "semanticType": "organization_name" },
      { "name": "domain_name",       "semanticType": "domain_name" },
      { "name": "email",             "semanticType": "email" },
      { "name": "phone",             "semanticType": "phone" },
      { "name": "address_line",      "semanticType": "address_line" },
      { "name": "postal_code",       "semanticType": "postal_code" }
    ]
  },
  "mergeConfiguration": {
    "mergeFields": [
      { "fieldName": "organization_name", "sourcePriority": ["CRM", "Marketing", "Support"] },
      { "fieldName": "domain_name",       "sourcePriority": ["CRM", "Marketing", "Support"] },
      { "fieldName": "email",             "sourcePriority": ["CRM", "Marketing", "Support"] },
      { "fieldName": "phone",             "sourcePriority": ["CRM", "Marketing", "Support"] },
      { "fieldName": "address_line",      "sourcePriority": ["CRM", "Marketing", "Support"] },
      { "fieldName": "postal_code",       "sourcePriority": ["CRM", "Marketing", "Support"] }
    ]
  },
  "autoStart": true
}
